am_active_learning/__init__.py
am_active_learning/src/__init__.py
am_active_learning/src/data_tools/__init__.py
am_active_learning/src/data_tools/data_viz.py
am_active_learning/src/data_tools/gpr.py
am_active_learning/src/data_tools/property.py
am_active_learning/src/data_tools/qNEHVI.py
am_active_learning/src/data_tools/sample_space.py
am_active_learning-0.2.2.dist-info/WHEEL
am_active_learning-0.2.2.dist-info/METADATA
am_active_learning-0.2.2.dist-info/RECORD
